{"cameraMode":{"drawMode":0,"name":"Shaded","section":"Shading Mode"},"sceneLighting":true,"audioPlay":false,"sceneViewState":{"m_AlwaysRefresh":false,"showFog":true,"showSkybox":true,"showFlares":true,"showImageEffects":true,"showParticleSystems":true,"showVisualEffectGraphs":true,"m_FxEnabled":true},"in2DMode":false,"pivot":{"x":-0.8253929615020752,"y":-1.4588227272033692,"z":4.242793560028076},"rotation":{"x":0.23647980391979218,"y":-0.636558473110199,"z":0.2144145369529724,"w":0.7020666599273682},"size":1.3088102340698243,"orthographic":false}